datalib/__init__.py
datalib/data_manipulation.py
datalib/ml.py
datalib/statistics.py
datalib/visualization.py
nf_datalib-0.1.0.dist-info/METADATA
nf_datalib-0.1.0.dist-info/WHEEL
nf_datalib-0.1.0.dist-info/licenses/LICENSE
nf_datalib-0.1.0.dist-info/RECORD
