Metadata-Version: 2.4
Name: nf-datalib
Version: 0.1.0
Summary: A Python library for data manipulation and analysis
Author-email: Nader Ferjani <ferjani.nader@hotmail.fr>
License-Expression: MIT
License-File: LICENSE
Requires-Python: >=3.8
Requires-Dist: matplotlib
Requires-Dist: numpy
Requires-Dist: pandas
Requires-Dist: scikit-learn
Requires-Dist: scipy>=1.10.0
Requires-Dist: seaborn>=0.12.0
Provides-Extra: doc
Requires-Dist: sphinx>=7.0; extra == 'doc'
Provides-Extra: test
Requires-Dist: pytest-cov>=4.0; extra == 'test'
Requires-Dist: pytest>=7.0; extra == 'test'
